ALU_8bit.v
module ALU_8bit(a,b,opcode,result);
  input [7:0]a,b;
  input [2:0]opcode;
  output reg [7:0]result;

  always @ (*) begin
    case(opcode)
      3'b000 : result = a + b;           //ADD
      3'b001 : result = a - b;           //SUB
      3'b010 : result = a & b;           //AND
      3'b011 : result = a | b;           //OR
      3'b100 : result = a ^ b;           //X-OR
      3'b101 : result = a << 1;          //SHIFT LEFT
      3'b110 : result = a >> 1;          //SHIFT RIGHT
      3'b111 : result = (a < b) ? 1 : 0; //SET LESS THAN(SLT)
      default : result = 0;
    endcase
  end
endmodule

ALU_testbench.v
`timescale 1ns/1ps
module ALU_tb;
  reg [7:0]a,b;
  reg [2:0]opcode;
  wire [7:0]result;

  //Instantiation
  ALU_8bit UUT(.a(a),.b(b),.opcode(opcode),.result(result));

  //Stimulus
  initial begin
  $dumpfile("ALU.vcd");
  $dumpvars(0,ALU_tb);
  $monitor($time,"ns a=%b | b=%b | opcode=%b | result=%b",a,b,opcode,result);
  
  a=8'd0; b=8'd0; opcode=3'b000;

  //ADD
  a=8'hA5; b=8'h5A; opcode=3'b000;
  #10;

  //SUB
  a=8'd25; b=8'd20; opcode=3'b001;
  #10;

  //AND
  a=8'hAA; b=8'h45; opcode=3'b010;
  #10;

  //OR
  opcode=3'b011;
  #10;

  //XOR
  opcode=3'b100;
  #10;
  
  //SHIFT LEFT
  opcode=3'b101;
  #10;

  //SHIFT RIGHT
  opcode=3'b110;
  #10;

  //SLT
  a=8'd10; b=8'd5; opcode=3'b111;
  #10;
  
  #10 $finish;

  end
endmodule

ALU.vcd
$date
	Mon Dec 01 17:34:57 2025
$end
$version
	Icarus Verilog
$end
$timescale
	1ps
$end
$scope module ALU_tb $end
$var wire 8 ! result [7:0] $end
$var reg 8 " a [7:0] $end
$var reg 8 # b [7:0] $end
$var reg 3 $ opcode [2:0] $end
$scope module UUT $end
$var wire 8 % a [7:0] $end
$var wire 8 & b [7:0] $end
$var wire 3 ' opcode [2:0] $end
$var reg 8 ( result [7:0] $end
$upscope $end
$upscope $end
$enddefinitions $end
$comment Show the parameter values. $end
$dumpall
$end
#0
$dumpvars
b11111111 (
b0 '
b1011010 &
b10100101 %
b0 $
b1011010 #
b10100101 "
b11111111 !
$end
#10000
b101 !
b101 (
b1 $
b1 '
b10100 #
b10100 &
b11001 "
b11001 %
#20000
b0 !
b0 (
b10 $
b10 '
b1000101 #
b1000101 &
b10101010 "
b10101010 %
#30000
b11101111 !
b11101111 (
b11 $
b11 '
#40000
b100 $
b100 '
#50000
b1010100 !
b1010100 (
b101 $
b101 '
#60000
b1010101 !
b1010101 (
b110 $
b110 '
#70000
b0 !
b0 (
b111 $
b111 '
b101 #
b101 &
b1010 "
b1010 %
